iSSVD/__init__.py
iSSVD/functions.py
iSSVD-0.1.5.dist-info/LICENSE.txt
iSSVD-0.1.5.dist-info/METADATA
iSSVD-0.1.5.dist-info/WHEEL
iSSVD-0.1.5.dist-info/top_level.txt
iSSVD-0.1.5.dist-info/RECORD
