Metadata-Version: 2.1
Name: iSSVD
Version: 0.1.5
Summary: Robust Integrative Biclustering for Multi-view Data
Home-page: https://github.com/weijie25/iSSVD
Author: Weijie Zhang
Author-email: zhan6385@umn.edu
License: UNKNOWN
Platform: UNKNOWN
Classifier: Programming Language :: Python :: 3
Classifier: License :: OSI Approved :: MIT License
Classifier: Operating System :: OS Independent
Requires-Python: >=3.5
